odoo/addons/ssi_partner_language/README.rst
odoo/addons/ssi_partner_language/__init__.py
odoo/addons/ssi_partner_language/__manifest__.py
odoo/addons/ssi_partner_language/models/__init__.py
odoo/addons/ssi_partner_language/models/partner_languange.py
odoo/addons/ssi_partner_language/models/res_partner.py
odoo/addons/ssi_partner_language/security/ir.model.access.csv
odoo/addons/ssi_partner_language/static/description/icon.png
odoo/addons/ssi_partner_language/views/res_partner_views.xml
odoo14_addon_ssi_partner_language-14.0.1.1.0.dist-info/METADATA
odoo14_addon_ssi_partner_language-14.0.1.1.0.dist-info/WHEEL
odoo14_addon_ssi_partner_language-14.0.1.1.0.dist-info/top_level.txt
odoo14_addon_ssi_partner_language-14.0.1.1.0.dist-info/RECORD
